[{"episodeId":"bike-001","title":"All About AI","shortDescription":"The guys talk about how they use AI, what are some of the footguns in how it's being used, and also share a bit of outlook on what it means to be an AI-first software engineer!","hosts":[{"name":"Scott Kaye","socials":{"bluesky":"https://bsky.app/profile/scottykaye.com","github":"https://github.com/scottykaye/","website":"https://scottykaye.com/"}},{"name":"Dillon Curry","socials":{"github":"https://github.com/illourr","website":"https://dilloncurry.vercel.app/"}},{"name":"Matt Hamlin","socials":{"bluesky":"https://bsky.app/profile/matthamlin.me","github":"https://github.com/hamlim/","website":"https://matthamlin.me/"}}],"metadata":["AI","Software Development"],"publishTime":1741646728409,"duration":3547,"longDescription":"\nimport {hosts} from '#/hosts'\nimport {Anchor} from '#/components/anchor'\n\n### All About AI\n\nThis week, <Anchor href={hosts.scott.socials.website}>Scott</Anchor>, <Anchor href={hosts.dillon.socials.website}>Dillon</Anchor>, and <Anchor href={hosts.matt.socials.website}>Matt</Anchor> talk about how they use AI, what are some of the footguns in how it's being used, and also share a bit of outlook on what it means to be an AI-first software engineer!\n","audioURL":"https://assets.bikeshedpod.com/episodes/bike-001/audio.mp3","captionURL":"https://assets.bikeshedpod.com/episodes/bike-001/captions.vtt"}]